data_rental_share/__init__.py
data_rental_share/main.py
data_rental_share/prompts.py
data_rental_share-2025.12.21194601.dist-info/METADATA
data_rental_share-2025.12.21194601.dist-info/WHEEL
data_rental_share-2025.12.21194601.dist-info/top_level.txt
data_rental_share-2025.12.21194601.dist-info/RECORD
