Metadata-Version: 2.4
Name: data-rental-share
Version: 2025.12.21194601
Summary: data-rental-share facilitates secure, temporary, and structured data sharing with defined rental terms, usage permissions, and expiration dates for transparency and manageability.
Author-email: data-rental-share <hi@eugene.plus>
License: MIT
Project-URL: Homepage, https://github.com/chigwell/data-rental-share
Requires-Python: >=3.9
Requires-Dist: langchain-llm7>=0.0.0
Requires-Dist: llmatch-messages>=0.0.0
Requires-Dist: langchain-core>=0.3.0
